MANIFEST.in
README.rst
setup.py
aliyun_python_sdk_zhuque.egg-info/PKG-INFO
aliyun_python_sdk_zhuque.egg-info/SOURCES.txt
aliyun_python_sdk_zhuque.egg-info/dependency_links.txt
aliyun_python_sdk_zhuque.egg-info/requires.txt
aliyun_python_sdk_zhuque.egg-info/top_level.txt
aliyunsdkzhuque/__init__.py
aliyunsdkzhuque/request/__init__.py
aliyunsdkzhuque/request/v20160701/AddCloudInstanceRequest.py
aliyunsdkzhuque/request/v20160701/AddCustomerRequest.py
aliyunsdkzhuque/request/v20160701/AddProjectRequest.py
aliyunsdkzhuque/request/v20160701/AddProjectVersion4PimsRequest.py
aliyunsdkzhuque/request/v20160701/ComputeMachineListRequest.py
aliyunsdkzhuque/request/v20160701/CopyProjectVersion4PimsRequest.py
aliyunsdkzhuque/request/v20160701/GetCloudInstanceDetailsRequest.py
aliyunsdkzhuque/request/v20160701/GetCurrentProjectStepRequest.py
aliyunsdkzhuque/request/v20160701/GetCustomerRequest.py
aliyunsdkzhuque/request/v20160701/GetProjectIdByBusinessInfoRequest.py
aliyunsdkzhuque/request/v20160701/GetProjectInfoRequest.py
aliyunsdkzhuque/request/v20160701/GetVersionIdByBusinessInfoRequest.py
aliyunsdkzhuque/request/v20160701/ListCloudInstanceRequest.py
aliyunsdkzhuque/request/v20160701/ListCommitRequest.py
aliyunsdkzhuque/request/v20160701/ListCustomerRequest.py
aliyunsdkzhuque/request/v20160701/ListMachineTypeGroupRequest.py
aliyunsdkzhuque/request/v20160701/ListProjectsByBusinessIdRequest.py
aliyunsdkzhuque/request/v20160701/ListProjectsRequest.py
aliyunsdkzhuque/request/v20160701/ListSelectedFeaturesRequest.py
aliyunsdkzhuque/request/v20160701/ModifyProject4pimsRequest.py
aliyunsdkzhuque/request/v20160701/ModifyProjectVersionPropertyModeRequest.py
aliyunsdkzhuque/request/v20160701/ModifyProjectVersionTypeRequest.py
aliyunsdkzhuque/request/v20160701/PhysicalServerCountRequest.py
aliyunsdkzhuque/request/v20160701/PhysicalServerMachineTypeCountRequest.py
aliyunsdkzhuque/request/v20160701/QueryLocationTreeRequest.py
aliyunsdkzhuque/request/v20160701/QueryProject4PimsRequest.py
aliyunsdkzhuque/request/v20160701/QueryZhuqueSummaryRequest.py
aliyunsdkzhuque/request/v20160701/SaveCloudInstanceRequest.py
aliyunsdkzhuque/request/v20160701/SaveMasterInputPlanRequest.py
